<?xml version="1.0" encoding="utf-8"?>
<LanguageData>

  <!-- Various -->
  <HitPointsBasic>Puntos de ataque</HitPointsBasic>
  <WorkLeft>Trabajo restante</WorkLeft>
  <Contents>Contenidos</Contents>
  <ContainedResources>Recursos contenidos</ContainedResources>
  <ForPrisonerUse>Para uso de prisioneros</ForPrisonerUse>
  <InPrisonCell>En una celda de prisión: Para uso de los prisioneros</InPrisonCell>
  <ForColonistUse>Para uso de colonos</ForColonistUse>
  <MedicalBed>Médica</MedicalBed>
  <Owner>Dueño</Owner>
  <Owners>Dueños</Owners>
  <AssignedColonist>Colono asignado</AssignedColonist>
  <DiedOn>Murió en el {0}</DiedOn>
  <Nobody>Nadie</Nobody>
  <Unowned>Sin dueño</Unowned>
  <DeadTime>Muerto hace {0}</DeadTime>
  <WalkSpeed>Factor de velocidad: {0}</WalkSpeed>
  <FertShort>Fert.</FertShort>
  <DyingLower>muriendo</DyingLower>
  <FilthOnFeet>Mugre en los pies:</FilthOnFeet>
  <NotEnoughStoredLower>No hay suficiente</NotEnoughStoredLower>
  <NothingLower>Nada</NothingLower>
  <Adapted>Adaptado</Adapted>
  <FreshMissingBodyPart>Fresco</FreshMissingBodyPart>
  <DevelopedImmunityLower>Inmunidad desarrollada</DevelopedImmunityLower>
  <NeedsTendingNow>Necesita tratamiento ahora</NeedsTendingNow>
  <CanTendNow>Puede atender ahora</CanTendNow>
  <TreatmentExpiresIn>El tratamiento expira en {0}</TreatmentExpiresIn>
  <NextTendIn>La siguiente dosis debe ser en {0}</NextTendIn>
  <TendQuality>Calidad del tratamiento</TendQuality>
  <MissingMedicalBillIngredient>No {0}</MissingMedicalBillIngredient>
  <Immunity>Inmunidad</Immunity>
  <Race>Especie</Race>
  <Description>Descripción</Description>
  <Equipment>Equipo</Equipment>
  <Apparel>Vestimenta</Apparel>
  <Inventory>Inventario</Inventory>
  <ThingInfo>Información</ThingInfo>
  <DropThing>Tirar</DropThing>
  <Rename>Renombrar</Rename>
  <RenameAnimal>Renombrar animal</RenameAnimal>
  <RenameColonist>Renombrar colono</RenameColonist>
  <UnknownLower>Desconocido</UnknownLower>
  <On>Encendido</On>
  <Off>Apagado</Off>
  <PowerSwitch_Power>Energía</PowerSwitch_Power>
  <JoyTolerances>Tolerancias</JoyTolerances>
  <MilkFullness>Producción de leche</MilkFullness>
  <WoolGrowth>Producción de lana</WoolGrowth>
  <EggProgress>Producción de huevo</EggProgress>
  <Fertilized>Fertilizado</Fertilized>
  <ProgressStoppedUntilFertilized>Producción detenida hasta la fertilización</ProgressStoppedUntilFertilized>
  <SkillTooLow>Necesita {0} nivel {2}, tiene {1}</SkillTooLow>
  <Freezing>Congelándose</Freezing>
  <Overheating>Sobrecalentándose</Overheating>
  <RuinedByTemperature>Arruinado por la temperatura.</RuinedByTemperature>
  <CorpsePercentMissing>Partes del cuerpo faltantes</CorpsePercentMissing>
  <HiveReproducesIn>Se reproduce en</HiveReproducesIn>
  <DormantHiveNotReproducing>Dormido: No se está reproduciendo.</DormantHiveNotReproducing>
  <NextSpawnedItemIn>Siguiente {0} en</NextSpawnedItemIn>
  <BrokenDown>Averiado</BrokenDown>
  <BondBrackets>(vínculo)</BondBrackets>
  <Fuel>Combustible</Fuel>
  <FuelLevelGizmoLabel>Combustible</FuelLevelGizmoLabel>
  <SetTargetFuelLevel>Designar nivel de combustible a {0}</SetTargetFuelLevel>
  <SetPodLauncherTargetFuelLevel>Designar nivel de combustible a {0}\nMax. distancia: {1} casillas</SetPodLauncherTargetFuelLevel>
  <ConfiguredTargetFuelLevel>Nivel de combustible objetivo: {0}</ConfiguredTargetFuelLevel>
  <Enemies>Enemigos</Enemies>
  <TimePassed>Tiempo transcurrrido</TimePassed>
  <CurrentRadius>Radio actual</CurrentRadius>
  <RadiusExpandsIn>Radio se expande en</RadiusExpandsIn>
  <Permanent>Permanente</Permanent>
  <CaravanResting>Descansando.</CaravanResting>
  <UsingBedroll>usando 1 cama enrrollable</UsingBedroll>
  <UsingBedrolls>usando {0} cama enrrollable</UsingBedrolls>
  <CaravanEstimatedTimeToDestination>Tiempo de llegada: {0}</CaravanEstimatedTimeToDestination>
  <CaravanEstimatedDaysToDestination>Días estimados de llegada: {0}</CaravanEstimatedDaysToDestination>
  <CaravanImmobilizedByMass>Inmobilizada: Peso excesivo.</CaravanImmobilizedByMass>
  <CaravanOutOfFood>Sin comida.</CaravanOutOfFood>
  <CaravanDaysOfFood>Queda comida para {0} días</CaravanDaysOfFood>
  <CaravanDaysOfFoodRot>Queda comida para: {0} días, se pudre en {1} días</CaravanDaysOfFoodRot>
  <AllCaravanMembersDowned>Detenida: Todos están inconscientes.</AllCaravanMembersDowned>
  <AllCaravanMembersMentalBreak>Detenida: Todos tienen un colapso mental.</AllCaravanMembersMentalBreak>
  <CaravanColonistsCount>{0} {1}</CaravanColonistsCount>
  <CaravanAnimal>1 animal</CaravanAnimal>
  <CaravanAnimalsCount>{0} animal</CaravanAnimalsCount>
  <CaravanPrisoner>1 prisionero</CaravanPrisoner>
  <CaravanPrisonersCount>{0} prisioneros</CaravanPrisonersCount>
  <CaravanPawnsInMentalState>{0} en estado mental</CaravanPawnsInMentalState>
  <CaravanPawnsDowned>{0} derribado</CaravanPawnsDowned>
  <CaravanTraveling>Viajando.</CaravanTraveling>
  <CaravanPaused>Pausado.</CaravanPaused>
  <CaravanWaiting>Esperando.</CaravanWaiting>
  <BeingCarriedDueToIllness>Siendo cargado por enfermedad</BeingCarriedDueToIllness>
  <UsingBedrollsDueToIllness>Usando sacos de dormir debido a una enfermedad</UsingBedrollsDueToIllness>
  <CurrentTileMovementTime>Velocidad actual</CurrentTileMovementTime>
  <Visibility>Visibilidad</Visibility>
  <Temperature>Temperatura</Temperature>
  <BadTemperature>Mala temperatura</BadTemperature>
  <IdealFermentingTemperature>Temperatura de fermentación ideal</IdealFermentingTemperature>
  <DrugEffectMultiplier>Multiplicador de efecto de {0}</DrugEffectMultiplier>
  <CaravanVisiting>Visitando {0}.</CaravanVisiting>
  <CaravanEntering>Entrando {0}.</CaravanEntering>
  <CaravanAttacking>Atacando {0}.</CaravanAttacking>
  <CaravanOfferingGifts>Ofreciendo regalos a {0}.</CaravanOfferingGifts>
  <WasWornByCorpse>Fue llevado por un cadaver.</WasWornByCorpse>
  <WornByCorpseChar>D</WornByCorpseChar>
  <DeterioratingUnroofed>Sin techo</DeterioratingUnroofed>
  <DeterioratingOutdoors>Exteriores</DeterioratingOutdoors>
  <DeterioratingBecauseOf>Se deteriora debido a</DeterioratingBecauseOf>
  <Map>Mapa</Map>
  <ForceExitAndRemoveMapCountdown>{0} hora para salida</ForceExitAndRemoveMapCountdown>
  <ForceExitAndRemoveMapCountdownTip>Tus colonos automáticamente reformarán la caravana y abandonarán el área al pasar {0} horas.</ForceExitAndRemoveMapCountdownTip>
  <Room>Habitación</Room>
  <BeautyHere>Belleza aquí</BeautyHere>
  <NoPower>Sin energía</NoPower>
  <WorkSpeedPenalty>Penalización de velocidad de trabajo</WorkSpeedPenalty>
  <DisabledCommand>DESACTIVADO</DisabledCommand>
  <ReadyForLaunch>Lista para el despegue.</ReadyForLaunch>
  <NotReadyForLaunch>No lista para el despegue</NotReadyForLaunch>
  <NotAllInGroupConnectedToFuelingPort>Sin puerto de recarga</NotAllInGroupConnectedToFuelingPort>
  <NotAllFuelingPortSourcesInGroupHaveAnyFuel>Sin combustible</NotAllFuelingPortSourcesInGroupHaveAnyFuel>
  <TransportPodInGroupHasSomethingLeftToLoad>Carga en progreso</TransportPodInGroupHasSomethingLeftToLoad>
  <TransportPodDestinationBeyondMaximumRange>Mas allá del rango máximo</TransportPodDestinationBeyondMaximumRange>
  <TransportPodNotEnoughFuel>Sin combustible suficiente</TransportPodNotEnoughFuel>
  <SettlementTrader>{0} de {1}</SettlementTrader>
  <RoomSurgerySuccessChanceFactor>Factor de probabilidad de éxito de la cirugía en la habitación</RoomSurgerySuccessChanceFactor>
  <RoomInfectionChanceFactor>Factor de probabilidad de infección en la habitación</RoomInfectionChanceFactor>
  <VentClosed>Cerrada</VentClosed>
  <WornBy>Usado por {0}</WornBy>
  <EquippedBy>Equipado por {0}</EquippedBy>
  <QuestTargetDestroyInspectString>{0} quiere que esto sea destruido.\n Recompensa: {1}.</QuestTargetDestroyInspectString>
  <WorldObjectTimeout>Tiempo restante: {0}</WorldObjectTimeout>
  <ItemStashContents>Contenidos: {0}.</ItemStashContents>
  <ClickToSortByThisColumn>Clic para ordenar por esta columna.</ClickToSortByThisColumn>
  <WorkPriorityShiftClickTip>Shift + clic: Incrementar la prioridad\nShift + clic derecho: Disminuir la prioridad</WorkPriorityShiftClickTip>
  <WorkPriorityShiftClickEnableDisableTip>Shift + clic: Activar todo\nShift + clic derecho: Desactivar todo</WorkPriorityShiftClickEnableDisableTip>
  <AllowedAreaShiftClickTip>Shift + clic: Permitir área segura\nShift + clic derecho: Sin restricciones</AllowedAreaShiftClickTip>
  <CheckboxShiftClickTip>Shift + clic: Revisar todo\nShift + clic derecho: No revisar</CheckboxShiftClickTip>
  <KnownSiteThreat>Amenaza: {0}.</KnownSiteThreat>
  <KnownSiteThreats>Amenazas: {0}.</KnownSiteThreats>
  <KnownSiteThreatsNone>Amenazas: ninguna.</KnownSiteThreatsNone>
  <SkillRequirements>Requerimientos de habilidad</SkillRequirements>
  <Products>Productos</Products>
  <Relationship>{0} de {1}</Relationship>
  <Prisoner>Prisionero</Prisoner>
  <Refugee>Refugiado</Refugee>
  <TileMovementDifficulty>Dificultad en el movimiento por el terreno</TileMovementDifficulty>
  <Impassable>Impasable</Impassable>
  <CaravanMovementSpeedFull>Velocidad de movimiento de la caravana</CaravanMovementSpeedFull>
  <DownedLower>Derribado</DownedLower>
  <Carried>Cargado</Carried>
  <AverageCaravanMemberMoveSpeed>Velocidad media de movimiento de la persona</AverageCaravanMemberMoveSpeed>
  <MultiplierForCarriedMass>Multiplicador de la masa transportada: {0}</MultiplierForCarriedMass>
  <FinalCaravanPawnsMovementSpeed>Velocidad de los miembros de la caravana</FinalCaravanPawnsMovementSpeed>
  <FinalCaravanMovementSpeed>Velocidad final</FinalCaravanMovementSpeed>
  <Winter>Invierno</Winter>
  <MovementDifficultyOffsetInWinter>{0} en invierno</MovementDifficultyOffsetInWinter>
  <RangeTo>a</RangeTo>
  <NoDietCategoryLetter>Ninguna carta</NoDietCategoryLetter>
  <ExpiresIn>Expira en</ExpiresIn>
  <CaravanLeaderCaravanName>Caravana de {0}</CaravanLeaderCaravanName>
  <Reason>Razón</Reason>
  <RelationsWith>Relaciones con {0}</RelationsWith>
  <capturedBy>Capturado por {0}</capturedBy>
  <yourCaravan>Tu caravana</yourCaravan>
  <CreatureWildness>Salvajismo de {0}</CreatureWildness>
  <CreatureTrainability>Adiestrabilidad de {0}</CreatureTrainability>
  <ProximitySingleGoodwillChange>{0} con {1}</ProximitySingleGoodwillChange>
  <EnterCooldown>No puede volver a entrar por otros {0} días.</EnterCooldown>
  <Caravan>Caravana</Caravan>
  <HiddenOrNoSitePartDescription>Puede haber peligro allí</HiddenOrNoSitePartDescription>
  <PreciousLumpLabel>pedazo de {0}</PreciousLumpLabel>
  <NoActiveResearchProjectToFinish>ningún proyecto de investigación activo</NoActiveResearchProjectToFinish>

  <!-- Fermentation barrel -->
  <ContainsWort>Contiene {0} / {1} de mosto.</ContainsWort>
  <ContainsBeer>Contiene {0} / {1} de cerveza.</ContainsBeer>
  <Fermented>Fermentado</Fermented>
  <FermentationProgress>Progreso: {0} (se termina en {1}).</FermentationProgress>
  <FermentationBarrelOutOfIdealTemperature>Temperatura no ideal. Multiplicador de velocidad de fermentación: {0}</FermentationBarrelOutOfIdealTemperature>

  <!--TextMotes-->
  <Headshot>Disparo a la cabeza</Headshot>
  <TextMote_TreatSuccess>¡Tratamiento exitoso! probabilidad del \n{0}</TextMote_TreatSuccess>
  <TextMote_TreatFailed>Tratamiento fallido, probabilidad del \n{0}</TextMote_TreatFailed>
  <TextMote_HarvestFailed>Cosecha\nfallida</TextMote_HarvestFailed>
  <TextMote_YieldWasted>Producción\nfallida</TextMote_YieldWasted>
  <TextMote_ProductWasted>Producción\nfallida</TextMote_ProductWasted>
  <TextMote_RecruitFail>Reclutamiento fallido probabilidad del \n{0}</TextMote_RecruitFail>
  <TextMote_ResistanceReduced>Resistencia\n{0} de {1}</TextMote_ResistanceReduced>
  <TextMote_TameFail>Domesticación fallida, probabilidad del \n{0}</TextMote_TameFail>
  <TextMote_TameSuccess>¡Domesticado! probabilidad del \n{0}</TextMote_TameSuccess>
  <TextMote_TrainFail>Entrenamiento fallido: probabilidad del {0}\n{1}</TextMote_TrainFail>
  <TextMote_TrainSuccess>Entrenado: probabilidad del {0}\n{1}</TextMote_TrainSuccess>
  <TextMote_FixBrokenDownBuildingFail>Reparación\nfallida</TextMote_FixBrokenDownBuildingFail>
  <TextMote_ConstructionFail>Construcción\nfallida</TextMote_ConstructionFail>
  <TextMote_Dodge>Esquivar</TextMote_Dodge>
  <TextMote_Tended>{0} atendido(a)</TextMote_Tended>
  <lowMood>humor bajo</lowMood>
  <lowOpinion>baja opinión</lowOpinion>

  <!-- Areas -->
  <Home>Hogar</Home>
  <BuildRoof>Construir techo</BuildRoof>
  <NoRoof>Sin techo</NoRoof>
  <SnowClear>Sin nieve</SnowClear>
  <AreaDefaultLabel>Área {0}</AreaDefaultLabel>
  <NoAreaAllowed>Sin restricciones</NoAreaAllowed>
  <NewArea>Nueva área</NewArea>
  <InvertArea>Invertir</InvertArea>

  <!-- Control -->
  <CannotOrderNonControlled>No dar órdenes a unidades ajenas.</CannotOrderNonControlled>
  <IsIncapableOfViolence>{0} es incapaz de violencia.</IsIncapableOfViolence>
  <IsIncapableOfViolenceShort>incapaz de violencia</IsIncapableOfViolenceShort>
  <IsNotDrafted>{0} no está reclutado.</IsNotDrafted>

  <!-- Snow -->
  <SnowNone>Sin nieve</SnowNone>
  <SnowDusting>Nieve (escasa)</SnowDusting>
  <SnowThin>Nieve (delgada)</SnowThin>
  <SnowMedium>Nieve (media)</SnowMedium>
  <SnowThick>Nieve (gruesa)</SnowThick>

  <!-- Turrets -->
  <GunInstalled>Instalada</GunInstalled>
  <MinimumRange>Rango mínimo</MinimumRange>
  <CanFireIn>Puede disparar</CanFireIn>
  <CannotFire>No puede disparar</CannotFire>
  <Roofed>Cubierto</Roofed>
  <ShellLoaded>Cartucho cargado</ShellLoaded>
  <ShellNotLoaded>Sin cargar</ShellNotLoaded>

  <!-- Job reports -->
  <ReportHaulingTo>Acarreando {0} a {1}.</ReportHaulingTo>
  <ReportHauling>Acarreando {0}.</ReportHauling>
  <ReportHaulingUnknown>Acarreando.</ReportHaulingUnknown>
  <ReportSleeping>Durmiendo.</ReportSleeping>
  <ReportResting>Descansando.</ReportResting>
  <WatchingSunrise>Admirando el amanecer</WatchingSunrise>
  <CloudWatching>Mirando las nubes</CloudWatching>
  <WatchingSunset>Admirando el atardecer</WatchingSunset>
  <Stargazing>Mirando las estrellas</Stargazing>
  <WatchingEclipse>Mirando el eclipse</WatchingEclipse>
  <WatchingAurora>Mirando la aurora.</WatchingAurora>
  <UsingVerb>Usando {0} en {1}.</UsingVerb>
  <AreaLower>Área</AreaLower>
  <ReportCowering>Acobardándose.</ReportCowering>
  <ReportStanding>De pie.</ReportStanding>
  <ReportExtinguishingFire>Extinguiendo el fuego.</ReportExtinguishingFire>
  <ReportExtinguishingFireOn>Extinguiendo el fuego en {0}.</ReportExtinguishingFireOn>
  <ReportDiggingUpCorpse>Desenterrando un cadávere.</ReportDiggingUpCorpse>

  <!-- Lord job reports -->
  <LordReportAttendingMarriageCeremony>Asistiendo a ceremonia de matrimonio</LordReportAttendingMarriageCeremony>
  <LordReportAttendingParty>Asistiendo a fiesta</LordReportAttendingParty>
  <LordReportFormingCaravan>Formándose para una caravana</LordReportFormingCaravan>

  <!-- Shooting report -->
  <WeaponMissRadius>Radio de fallo del arma</WeaponMissRadius>
  <ShootReportShooterAbility>Tirador</ShootReportShooterAbility>
  <ShootReportWeapon>Arma</ShootReportWeapon>
  <Darkness>Oscuridad</Darkness>
  <TargetProne>Objetivo a cubierto</TargetProne>
  <TargetSize>Tamaño del objetivo</TargetSize>
  <Weather>Clima</Weather>
  <ShootingCover>Cobertura</ShootingCover>
  <CoverThingBlocksPercentOfShots>{0} detiene el {1}</CoverThingBlocksPercentOfShots>
  <NoCoverLower>Sin cobertura</NoCoverLower>
  <Execution>Ejecución</Execution>

  <!-- Generated recipes -->
  <RecipeMake>Fabricar {0}</RecipeMake>
  <RecipeMakeJobString>Haciendo {0}.</RecipeMakeJobString>
  <RecipeAdminister>Administrar {0}</RecipeAdminister>
  <RecipeAdministerJobString>Administrando {0}.</RecipeAdministerJobString>
  <TeetotalerUnhappy>El abstemio estará desdichado</TeetotalerUnhappy>
  <ProsthophobeUnhappy>El sujeto con anhelo de partes biónicas estará desdichado</ProsthophobeUnhappy>

  <!-- Thoughts -->
  <ThoughtExpiresIn>Expira en: {0}</ThoughtExpiresIn>
  <ThoughtStartsExpiringIn>Empieza a expirar en: {0}</ThoughtStartsExpiringIn>
  <ThoughtFinishesExpiringIn>Termina de expirar en: {0}</ThoughtFinishesExpiringIn>
  <MentalBreakThresholdExtreme>Límite de colapso mental extremo</MentalBreakThresholdExtreme>
  <MentalBreakThresholdMajor>Límite de colapso mental mayor</MentalBreakThresholdMajor>
  <MentalBreakThresholdMinor>Límite de colapso mental menor</MentalBreakThresholdMinor>

  <!-- Pawn info readout -->
  <PawnMainDescGendered>{1} {0}</PawnMainDescGendered>
  <PawnMainDescFactionedWrap>{0} de {1}</PawnMainDescFactionedWrap>
  <PawnMainDescLifestageWrap>{0} {1}</PawnMainDescLifestageWrap>
  <Faction>Facción</Faction>
  <Equipped>Equipamiento</Equipped>
  <EquippedNothing>Nada</EquippedNothing>
  <Dead>Muerto</Dead>
  <Unconscious>Inconsciente</Unconscious>
  <PainShock>En shock por el dolor</PainShock>
  <PainShockShort>Shock por panico</PainShockShort>
  <Incapacitated>Incapacitado</Incapacitated>
  <InRestraints>Encadenado (ralentizado)</InRestraints>
  <Carrying>Llevando</Carrying>
  <AffectedBy>Afectado por:</AffectedBy>
  <Queued>En cola</Queued>
  <State>Estado</State>
  <StunLower>Aturdir</StunLower>

  <!-- Inspector general stuff -->
  <SelectNextInSquareTip>Selecciona la siguiente cosa en el mismo cuadro.\n\nTecla de atajo: {0}\n\nPuedes hacer esto al hacer click lentamente en el mismo cuadro repetidas veces.</SelectNextInSquareTip>
  <DefInfoTip>Ver información sobre este objeto.</DefInfoTip>

  <!-- Hostility response -->
  <HostilityReponseTip>Cambia cómo reaccionar a los enemigos cercanos cuando el colono no está reclutado.</HostilityReponseTip>
  <HostilityResponseCurrentMode>Modo actual</HostilityResponseCurrentMode>

  <!-- like 'Blood of John' -->
  <OfLower>de</OfLower>

  <!-- Power readout -->
  <PowerNotConnected>Sin energía.</PowerNotConnected>
  <PowerConnectedRateStored>Energía sobrante/almacenada: {0} W / {1} Wd</PowerConnectedRateStored>
  <PowerNeeded>Energía necesaria</PowerNeeded>
  <PowerOutput>Energía generada</PowerOutput>
  <PowerBatteryStored>Energía almacenada</PowerBatteryStored>
  <PowerBatteryEfficiency>Eficiencia</PowerBatteryEfficiency>
  <SelfDischarging>Autodescarga</SelfDischarging>

  <!-- Temperature control -->
  <TargetTemperature>Temperatura objetivo</TargetTemperature>
  <PowerConsumptionMode>Uso de energía actual</PowerConsumptionMode>
  <PowerConsumptionHigh>Alto</PowerConsumptionHigh>
  <PowerConsumptionLow>Bajo</PowerConsumptionLow>

  <!-- Temperature readout -->
  <Indoors>Interiores</Indoors>
  <IndoorsUnroofed>Sin techo</IndoorsUnroofed>
  <Outdoors>Exteriores</Outdoors>

  <!--Rotting-->
  <RotStateFresh>Fresco</RotStateFresh>
  <RotStateRotting>Podrido</RotStateRotting>
  <RotStateDessicated>Desecado</RotStateDessicated>
  <CurrentlyFrozen>Congelado (no se pudrirá)</CurrentlyFrozen>
  <CurrentlyRefrigerated>Refrigerado (se pudre en {0})</CurrentlyRefrigerated>
  <NotRefrigerated>Sin refrigerar (se pudre en {0})</NotRefrigerated>
  <OverADecade>Más de una década</OverADecade>
  <LessThanADay>Menos de un día</LessThanADay>

  <!-- Shooting tooltip -->
  <ShotBy>Probabilidad de \nacierto de {0}</ShotBy>
  <CannotHit>Imposible impactar el objetivo.</CannotHit>
  <ManhunterPerHit>Probabilidad de cazahombres por impacto</ManhunterPerHit>

  <!-- Meal -->
  <Ingredients>Ingredientes</Ingredients>

  <!-- Plants -->
  <PercentGrowth>Crecimiento al {0}</PercentGrowth>
  <GrowthRate>Tasa de crecimiento actual</GrowthRate>
  <FullyGrownIn>Crecerá por completo al {0} de crecimiento.</FullyGrownIn>
  <PlantNeedsLightLevel>Necesita más luz</PlantNeedsLightLevel>
  <PlantResting>Descansando</PlantResting>
  <OutOfIdealTemperatureRange>Fuera del rango ideal de temperatura (creciendo al {0}% de la velocidad normal)</OutOfIdealTemperatureRange>
  <OutOfIdealTemperatureRangeNotGrowing>Fuera del rango ideal de temperatura (no está creciendo)</OutOfIdealTemperatureRangeNotGrowing>
  <ReadyToHarvest>Lista para cosechar.</ReadyToHarvest>
  <Mature>Madura.</Mature>
  <OutdoorGrowingPeriod>Periodo de crecimiento</OutdoorGrowingPeriod>
  <NoGrowingPeriod>Nunca</NoGrowingPeriod>
  <GrowYearRound>Todo el año</GrowYearRound>
  <GrowSeasonHereNow>Temporada de cultivo: Ahora.</GrowSeasonHereNow>
  <CannotGrowBadSeasonTemperature>Crecimiento imposible (pésima temperatura).</CannotGrowBadSeasonTemperature>
  <Blighted>Marchita</Blighted>
  <DyingBecauseExposedToLight>Muriendo porque está expuesta a la luz</DyingBecauseExposedToLight>

  <!-- Zones -->
  <Zone>Área</Zone>
  <GrowingZone>Área de cultivo</GrowingZone>
  <Stockpile>Almacén</Stockpile>
  <DumpingStockpile>Vertedero</DumpingStockpile>
  <Priority>Prioridad</Priority>
  <ClearAll>Nada</ClearAll>
  <AllowAll>Todo</AllowAll>

  <!-- ThingFilter -->
  <HitPoints>{0} puntos de daño</HitPoints>
  <AnyQuality>Cualquier calidad</AnyQuality>
  <OnlyQuality>{0} solamente</OnlyQuality>

  <!-- Mouseover indicator -->
  <Undiscovered>Sin descubrir</Undiscovered>

  <!-- Buttons -->
  <ShowLearningHelperWhenEmptyToggleButton>Alternar la visibilidad del asistente de aprendizaje cuando está vacío.\n\nEl asistente de aprendizaje siempre está visible si hay algún concepto activado para aprendizaje. Esto lo hace desaparecer cuando ningún concepto está activo.</ShowLearningHelperWhenEmptyToggleButton>
  <ZoneVisibilityToggleButton>Alternar la visibilidad de las áreas.</ZoneVisibilityToggleButton>
  <ShowBeautyToggleButton>Cambia el visor de belleza.\n\nMuestra la belleza del mundo tal y como la percibiría un personaje parado donde apunta el ratón.</ShowBeautyToggleButton>
  <ShowRoomStatsToggleButton>Cambiar la visualización de las estadísticas de la sala.\n\nMuestra las estadísticas de la habitación a la que apunta el ratón.</ShowRoomStatsToggleButton>
  <ShowColonistBarToggleButton>Alternar barra de colonos.\n\nMuestra los íconos y el estado básico de todos los colonos en la parte superior de la pantalla.</ShowColonistBarToggleButton>
  <AutoHomeAreaToggleButton>Alternar la expansión automática del área del hogar alrededor de construcciones nuevas.</AutoHomeAreaToggleButton>
  <AutoRebuildButton>Alternar la reconstrucción automática de estructuras destruidas.</AutoRebuildButton>
  <CategorizedResourceReadoutToggleButton>Alternar el modo categorizado de la lista de recursos.</CategorizedResourceReadoutToggleButton>
  <ShowAnimalNamesToggleButton>Alternar la visualización de los nombres de los animales domésticos.</ShowAnimalNamesToggleButton>
  <ShowRoofOverlayToggleButton>Alternar visibilidad de techos.</ShowRoofOverlayToggleButton>
  <LockNorthUpToggleButton>Impide la rotación de la cámara para que el polo norte siempre se encuentre arriba.</LockNorthUpToggleButton>
  <UsePlanetDayNightSystemToggleButton>Alternar el sistema de iluminación día/noche.</UsePlanetDayNightSystemToggleButton>
  <ShowExpandingIconsToggleButton>Alternar la visualización de íconos desplegables en lugar de los íconos regulares para objetos distantes</ShowExpandingIconsToggleButton>
  <ShowWorldFeaturesToggleButton>Alternar la visibilidad de los nombres de los accidentes geográficos.</ShowWorldFeaturesToggleButton>

  <!-- Fire -->
  <Fire>Fuego</Fire>
  <FireOn>Fuego en {0}</FireOn>
  <Burning>Quemándose</Burning>
  <FireSizeLower>Tamaño del fuego {0}</FireSizeLower>

  <!-- Game conditions -->
  <GameConditionsTip>Condiciones especiales que afectan el área en estos momentos.</GameConditionsTip>
  <TimeLeft>Tiempo restante</TimeLeft>
  <ImpactDate>Fecha de impacto</ImpactDate>

  <!-- Building placement -->
  <NoStuffsToBuildWith>No tienes materiales disponibles para construir esto.</NoStuffsToBuildWith>

  <!-- Building placement restricters -->
  <WillGetWorkSpeedPenalty>{0} tendrá una penalización a la velocidad de trabajo.</WillGetWorkSpeedPenalty>
  <MustPlaceUnroofed>No se puede ubicar bajo techo.</MustPlaceUnroofed>
  <MustPlaceHeadOnShipBeam>Se debe ubicar con el frente adyacente a la viga estructural de una nave.</MustPlaceHeadOnShipBeam>
  <MustPlaceNextToHopperAccepter>Se debe ubicar adyacente a un aparato que necesite una tolva.</MustPlaceNextToHopperAccepter>
  <MustPlaceOnSteamGeyser>Se debe ubicar directamente sobre un géiser de vapor.</MustPlaceOnSteamGeyser>
  <MustPlaceCoolerWithFreeSpaces>Ambos lados del refrigerador deben estar libres.</MustPlaceCoolerWithFreeSpaces>
  <MustPlaceVentWithFreeSpaces>Ambos lados deben estar libres para que el aire pueda circular.</MustPlaceVentWithFreeSpaces>
  <MustPlaceAdjacentStandable>Debe colocarse con espacio libre en todos los lados.</MustPlaceAdjacentStandable>
  <MustPlaceNearFuelingPort>Se debe situar a un costado de un puerto de recarga de una lanzadera de cápsulas.</MustPlaceNearFuelingPort>
  <MustPlaceOnDrillable>Debe colocarse en recursos perforables.</MustPlaceOnDrillable>

  <!-- Wind Turbine -->
  <WindTurbine_WindPathIsBlockedBy>Bloqueado por</WindTurbine_WindPathIsBlockedBy>
  <WindTurbine_WindPathIsBlockedByRoof>Bloqueado por techo</WindTurbine_WindPathIsBlockedByRoof>

  <!-- Watermill generator -->
  <Watermill_WaterUsedTwice>Flujo reducido: Turbulencia de otros molinos de agua</Watermill_WaterUsedTwice>

  <!-- Cryptosleep casket -->
  <CasketContains>Contiene</CasketContains>
  <CasketWarning>¡Peligro!¡\n\n[PAWN_nameDef] es tu último colono en pie! Si lo dejas entrar en ése sarcófago no podrás seguir jugando. ¿Estás seguro que quieres continuar?</CasketWarning>

  <!-- Ship launch report -->
  <ShipReportCannotLaunch>Lanzamiento imposible.</ShipReportCannotLaunch>
  <ShipReportCanLaunch>Listo para el lanzamiento.</ShipReportCanLaunch>
  <ShipReportMissingPart>Falta un componente crítico</ShipReportMissingPart>
  <ShipReportMissingPartRequires>Requiere</ShipReportMissingPartRequires>
  <ShipReportNoFullPods>No hay sarcófagos de criptosueño ocupados</ShipReportNoFullPods>
  <ShipReportHibernating>Componente de hibernación</ShipReportHibernating>
  <ShipReportNotReady>Componente aún no está listo</ShipReportNotReady>
  <HibernateWarning>Charlon Whitestone está listo para comenzar la secuencia de recuperación de la hibernación del reactor.\n\nAdvierte que el proceso tomará alrededor de 15 días, y la firma de la energía será detectable desde una gran distancia. Este tipo de firma de energía indica capacidad de vuelo interestelar y atraerá a bandas de asaltantes desesperados y cazadores de tesoros. Asegúrate de que tus defensas estén preparadas primero.</HibernateWarning>
  <HibernateWarningStandalone>El reactor está listo para encenderse.\n\nEl proceso tomará alrededor de 15 días, y la señal de energía será detectable a larga distancia. Este tipo de señal de energía indica la capacidad de vuelo interestelar, y atraerá a bandas de asaltantes desesperados y cazadores de tesoros. Asegúrese de que sus defensas estén preparadas primero.</HibernateWarningStandalone>
  <HibernateWarningPacifist>Charlon Whitestone está listo para iniciar la secuencia de recuperación de hibernación del reactor. Le advierte que el proceso durará unos 15 días.</HibernateWarningPacifist>
  <HibernateWarningStandalonePacifist>El reactor está listo para encenderse. El proceso durará unos 15 días.</HibernateWarningStandalonePacifist>

  <!-- Neurotrainer -->
  <NeurotrainerUsed>{0} usó {1} neuroentrenador(es) para ir del nivel {2} al nivel {3}.</NeurotrainerUsed>

  <!-- Minification -->
  <Installed>Instalado</Installed>
  <NotInstalled>No instalado</NotInstalled>

  <!-- Art -->
  <Title>Título</Title>
  <Untitled>Sin título</Untitled>

  <!-- Unfinished thing -->
  <UnfinishedItem>{0} sin acabar</UnfinishedItem>
  <UnfinishedItemWithStuff>{1} de {0} sin acabar</UnfinishedItemWithStuff>

  <!-- Quality -->
  <Quality>Calidad</Quality>
  <QualityDescription>La calidad es la medida de lo bien hecho que está un objeto.</QualityDescription>
  <QualityIs>Calidad: {0}</QualityIs>

  <!-- Mood descriptions -->
  <Mood_MentalState>Estado mental</Mood_MentalState>
  <Mood_AboutToBreak>Colapsando</Mood_AboutToBreak>
  <Mood_OnEdge>Nervioso</Mood_OnEdge>
  <Mood_Stressed>Estresado</Mood_Stressed>
  <Mood_Neutral>Neutral</Mood_Neutral>
  <Mood_Content>Contento</Mood_Content>
  <Mood_Happy>Feliz</Mood_Happy>

  <!-- Game over -->
  <GameOverEveryoneDead>Todos los habitantes de la colonia han muerto o se han ido. Esta historia se acabó.\n\nTal vez alguien le encuentre un uso a estas ruinas en el futuro...</GameOverEveryoneDead>
  <GameOverShipLaunched>¡Haz lanzado la nave! Estos colonos escaparon:\n\n{0}\nEstos colonos se han quedado atrás:\n\n{1}\nAhora la IA intentará guiar a la nave hacia un lugar seguro. Podría encontrar un planeta próspero en este mismo sistema o podría realizar un viaje de siglos hacia otra estrella. Incluso podría decidir quedarse bajo un asteroide por unos cuantos miles de años, esperando que alguien convierta este planeta en un mundobrillante.\n\nLo sabrás cuando despiertes...</GameOverShipLaunched>
  <GameOverPlanetkillerImpact>A casi la velocidad de la luz, el arma destruyeplanetas se estrelló contra el suelo con la energía de un trillón de bombas de hidrógeno. Como si fuera un globo con agua al que le han disparado con un rifle, el planeta se licúa con el impacto y dispersa su interior líquido a travéz del cosmos.\n\nUna parte de {0} ahora es un cinturón de asteroides. El resto es un páramo radioactivo e infernal azotado constantemente por terremotos de nivel planetario.\n\nNo sobreviviste.</GameOverPlanetkillerImpact>
  <GameOverArrivedAtJourneyDestination>Al subir a bordo de la nave, te saluda la tripulación con los brazos abiertos. Parecen alegrarse de poder tener al menos una persona más con ellos.\n\nThese colonists escaped:\n\n{0}\nEstos colonos fueron abandonados:\n\n{1}\nLa IA ahora intentará guiar a la nave a un lugar seguro. Podría encontrarte un planeta prospero en éste mismo sistema o podría realizar un viaje de varios siglos hacia otra estrella. Incluso podría decidir quedarse bajo un asteroide por unos cuantos miles de años, esperando que alguien convierta este planeta en un mundobrillante.\n\nLo sabrás cuando despiertes...</GameOverArrivedAtJourneyDestination>
  <GameOverKeepPlaying>Seguir jugando</GameOverKeepPlaying>
  <GameOverMainMenu>Menú principal</GameOverMainMenu>

  <!-- Generic lifespan -->
  <LifespanExpiry>Expira en:</LifespanExpiry>

  <!-- Traps -->
  <TrapArmed>Armada</TrapArmed>
  <TrapNotArmed>Sin armar</TrapNotArmed>
  <TrapRearmingCost>Costo del rearme: {0}</TrapRearmingCost>

  <!-- Facilities -->
  <InactiveFacility>Inactiva</InactiveFacility>

  <!-- Hediffs growth modes -->
  <DiseaseGrowthModeChanged_Growing>El {1} de {0} está creciendo.</DiseaseGrowthModeChanged_Growing>
  <DiseaseGrowthModeChanged_Stable>El {1} de {0} está estable.</DiseaseGrowthModeChanged_Stable>
  <DiseaseGrowthModeChanged_Remission>El {1} de {0} está en remisión.</DiseaseGrowthModeChanged_Remission>

  <!-- Marriage spot -->
  <MarriageSpotUsable>Usable.</MarriageSpotUsable>
  <MarriageSpotNotUsable>No usable: {0}.</MarriageSpotNotUsable>
  <MarriageSpotNotStandable>Bloqueado</MarriageSpotNotStandable>
  <MarriageSpotDangerous>Demasiado peligroso para {0}</MarriageSpotDangerous>
  <MarriageSpotForbidden>Prohibido para {0}</MarriageSpotForbidden>
  <MarriageSpotReserved>Reservado</MarriageSpotReserved>
  <MarriageSpotUnreachable>Inalcanzable para {0}</MarriageSpotUnreachable>
  <MarriageSpotInPrisonCell>En prisión</MarriageSpotInPrisonCell>
  <NotEnjoyableOutsideTemperature>Temperatura incómoda</NotEnjoyableOutsideTemperature>

  <!-- Colonist bar -->
  <ActivityIconMedicalRest>Descanso médico</ActivityIconMedicalRest>
  <ActivityIconSleeping>Durmiendo</ActivityIconSleeping>
  <ActivityIconFleeing>Huyendo</ActivityIconFleeing>
  <ActivityIconAttacking>Luchando</ActivityIconAttacking>
  <ActivityIconIdle>Ocioso</ActivityIconIdle>
  <ActivityIconBurning>Quemándose</ActivityIconBurning>
  <ActivityIconFormingCaravan>Formando una caravana</ActivityIconFormingCaravan>

  <!-- Maintainable -->
  <DueForMaintenance>Necesita mantenimiento.</DueForMaintenance>
  <DeterioratingDueToLackOfMaintenance>Deteriorándose debido a la falta de mantenimiento.</DeterioratingDueToLackOfMaintenance>

  <!-- Deep drill -->
  <ProgressToNextLump>Progreso hacia el siguiente lote</ProgressToNextLump>
  <ResourceBelow>Recursos debajo</ResourceBelow>
  <ProgressToNextPortion>Progreso a la siguiente porción</ProgressToNextPortion>
  <DeepDrillNoResources>No hay recursos abajo.</DeepDrillNoResources>
  <DeepDrillExhausted>Se agotan los recursos de las perforaciones en profundidad.</DeepDrillExhausted>
  <DeepDrillExhaustedNoFallback>Recursos profundos de perforación agotados.</DeepDrillExhaustedNoFallback>

  <!-- Learning helper -->
  <LearningHelper>Asistente de aprendizaje</LearningHelper>
  <MarkLearned>Aprendido</MarkLearned>
  <AlreadyLearned>Ya aprendido</AlreadyLearned>
  <Filter>Filtro</Filter>

  <!-- Compass -->
  <CompassTip>Muestra la dirección del norte. Haz click para rotar la cámara de manera que el norte se encuentre arriba.</CompassTip>

  <!-- World route planner -->
  <RoutePlannerButtonTip>Haga clic para ingresar al modo de planificación donde puede planificar su viaje y calcular la distancia entre puntos de referencia.</RoutePlannerButtonTip>
  <RoutePlannerAddTwoOrMoreWaypoints>Agregar dos o más puntos.</RoutePlannerAddTwoOrMoreWaypoints>
  <RoutePlannerAddOneOrMoreWaypoints>Agregar uno o más puntos.</RoutePlannerAddOneOrMoreWaypoints>
  <RoutePlannerEstTimeToFinalDest>Tiempo total de la ruta: {0}</RoutePlannerEstTimeToFinalDest>
  <RoutePlannerUsingAverageTicksPerMoveWarning>El modo de planificación usa la velocidad de la caravana predeterminada. Tu velocidad puede variar.</RoutePlannerUsingAverageTicksPerMoveWarning>
  <RoutePlannerUsingTicksPerMoveOfCaravan>Calculando para: {0}</RoutePlannerUsingTicksPerMoveOfCaravan>
  <RoutePlannerPressRMBToAddAndRemoveWaypoints>Botón derecho del mouse: Agregar/eliminar puntos de ruta.</RoutePlannerPressRMBToAddAndRemoveWaypoints>
  <RoutePlannerPressEscapeToExit>ESC: Salir del modo de planeación.</RoutePlannerPressEscapeToExit>
  <RoutePlannerPressEscapeToReturnToCaravanFormationDialog>ESC: Retornar al diálogo de formación de la caravana.</RoutePlannerPressEscapeToReturnToCaravanFormationDialog>
  <EstimatedTimeToWaypoint>Tiempo estimado de viaje: {0}</EstimatedTimeToWaypoint>
  <EstimatedTimeToWaypointFromPrevious>Tiempo estimado de viaje (desde el punto de ruta anterior): {0}</EstimatedTimeToWaypointFromPrevious>
  <EstimatedTimeToTile>Tiempo estimado de viaje: {0}</EstimatedTimeToTile>
  <ForagedFoodAmount>Cantidad de forraje</ForagedFoodAmount>

  <!-- Outfits -->
  <OutfitAnything>Cualquier cosa</OutfitAnything>
  <OutfitWorker>Trabajador</OutfitWorker>
  <OutfitSoldier>Soldado</OutfitSoldier>
  <OutfitNudist>Nudista</OutfitNudist>

  <!-- Hibernatable -->
  <HibernatableHibernating>Hibernando</HibernatableHibernating>
  <HibernatableStartingUp>Empezando</HibernatableStartingUp>

  <!-- Transport pods -->
  <ClickToSeeAvailableOrders_WorldObject>{0}: Ver ordenes disponibles...</ClickToSeeAvailableOrders_WorldObject>
  <ClickToSeeAvailableOrders_Empty>Ver ordenes disponibles...</ClickToSeeAvailableOrders_Empty>

</LanguageData>
