<?xml version="1.0" encoding="utf-8" ?>
<LanguageData>

  <QuadrupedAnimalWithPaws.label>Animal Cuadrúpedo</QuadrupedAnimalWithPaws.label>
  <QuadrupedAnimalWithPaws.corePart.parts.3.customLabel>Pulmón izquierdo</QuadrupedAnimalWithPaws.corePart.parts.3.customLabel>
  <QuadrupedAnimalWithPaws.corePart.parts.4.customLabel>Pulmón derecho</QuadrupedAnimalWithPaws.corePart.parts.4.customLabel>
  <QuadrupedAnimalWithPaws.corePart.parts.5.customLabel>Riñón izquierdo</QuadrupedAnimalWithPaws.corePart.parts.5.customLabel>
  <QuadrupedAnimalWithPaws.corePart.parts.6.customLabel>Riñón derecho</QuadrupedAnimalWithPaws.corePart.parts.6.customLabel>
  <QuadrupedAnimalWithPaws.corePart.parts.8.parts.0.parts.1.customLabel>Ojo izquierdo</QuadrupedAnimalWithPaws.corePart.parts.8.parts.0.parts.1.customLabel>
  <QuadrupedAnimalWithPaws.corePart.parts.8.parts.0.parts.2.customLabel>Ojo derecho</QuadrupedAnimalWithPaws.corePart.parts.8.parts.0.parts.2.customLabel>
  <QuadrupedAnimalWithPaws.corePart.parts.8.parts.0.parts.3.customLabel>Oído izquierdo</QuadrupedAnimalWithPaws.corePart.parts.8.parts.0.parts.3.customLabel>
  <QuadrupedAnimalWithPaws.corePart.parts.8.parts.0.parts.4.customLabel>Oído derecho</QuadrupedAnimalWithPaws.corePart.parts.8.parts.0.parts.4.customLabel>
  <QuadrupedAnimalWithPaws.corePart.parts.9.parts.0.customLabel>Pata delantera izquierda</QuadrupedAnimalWithPaws.corePart.parts.9.parts.0.customLabel>
  <QuadrupedAnimalWithPaws.corePart.parts.9.customLabel>Pie izquierdo delantero</QuadrupedAnimalWithPaws.corePart.parts.9.customLabel>
  <QuadrupedAnimalWithPaws.corePart.parts.10.parts.0.customLabel>Pata delantera derecha</QuadrupedAnimalWithPaws.corePart.parts.10.parts.0.customLabel>
  <QuadrupedAnimalWithPaws.corePart.parts.10.customLabel>Pie derecho delantero</QuadrupedAnimalWithPaws.corePart.parts.10.customLabel>
  <QuadrupedAnimalWithPaws.corePart.parts.11.parts.0.customLabel>Pata trasera izquierda</QuadrupedAnimalWithPaws.corePart.parts.11.parts.0.customLabel>
  <QuadrupedAnimalWithPaws.corePart.parts.11.customLabel>Pie izquierdo trasero</QuadrupedAnimalWithPaws.corePart.parts.11.customLabel>
  <QuadrupedAnimalWithPaws.corePart.parts.12.parts.0.customLabel>Pata trasera derecha</QuadrupedAnimalWithPaws.corePart.parts.12.parts.0.customLabel>
  <QuadrupedAnimalWithPaws.corePart.parts.12.customLabel>Pie trasero derecho</QuadrupedAnimalWithPaws.corePart.parts.12.customLabel>

  <QuadrupedAnimalWithPawsAndTail.label>Animal Cuadrúpedo</QuadrupedAnimalWithPawsAndTail.label>
  <QuadrupedAnimalWithPawsAndTail.corePart.parts.4.customLabel>Pulmón izquierdo</QuadrupedAnimalWithPawsAndTail.corePart.parts.4.customLabel>
  <QuadrupedAnimalWithPawsAndTail.corePart.parts.5.customLabel>Pulmón derecho</QuadrupedAnimalWithPawsAndTail.corePart.parts.5.customLabel>
  <QuadrupedAnimalWithPawsAndTail.corePart.parts.6.customLabel>Riñón izquierdo</QuadrupedAnimalWithPawsAndTail.corePart.parts.6.customLabel>
  <QuadrupedAnimalWithPawsAndTail.corePart.parts.7.customLabel>Riñón derecho</QuadrupedAnimalWithPawsAndTail.corePart.parts.7.customLabel>
  <QuadrupedAnimalWithPawsAndTail.corePart.parts.9.parts.0.parts.1.customLabel>Ojo izquierdo</QuadrupedAnimalWithPawsAndTail.corePart.parts.9.parts.0.parts.1.customLabel>
  <QuadrupedAnimalWithPawsAndTail.corePart.parts.9.parts.0.parts.2.customLabel>Ojo derecho</QuadrupedAnimalWithPawsAndTail.corePart.parts.9.parts.0.parts.2.customLabel>
  <QuadrupedAnimalWithPawsAndTail.corePart.parts.9.parts.0.parts.3.customLabel>Oído izquierdo</QuadrupedAnimalWithPawsAndTail.corePart.parts.9.parts.0.parts.3.customLabel>
  <QuadrupedAnimalWithPawsAndTail.corePart.parts.9.parts.0.parts.4.customLabel>Oído derecho</QuadrupedAnimalWithPawsAndTail.corePart.parts.9.parts.0.parts.4.customLabel>
  <QuadrupedAnimalWithPawsAndTail.corePart.parts.10.parts.0.customLabel>Pata delantera izquierda</QuadrupedAnimalWithPawsAndTail.corePart.parts.10.parts.0.customLabel>
  <QuadrupedAnimalWithPawsAndTail.corePart.parts.10.customLabel>Pie izquierdo delantero</QuadrupedAnimalWithPawsAndTail.corePart.parts.10.customLabel>
  <QuadrupedAnimalWithPawsAndTail.corePart.parts.11.parts.0.customLabel>Pata delantera derecha</QuadrupedAnimalWithPawsAndTail.corePart.parts.11.parts.0.customLabel>
  <QuadrupedAnimalWithPawsAndTail.corePart.parts.11.customLabel>Pie derecho delantero</QuadrupedAnimalWithPawsAndTail.corePart.parts.11.customLabel>
  <QuadrupedAnimalWithPawsAndTail.corePart.parts.12.parts.0.customLabel>Pata trasera izquierda</QuadrupedAnimalWithPawsAndTail.corePart.parts.12.parts.0.customLabel>
  <QuadrupedAnimalWithPawsAndTail.corePart.parts.12.customLabel>Pie izquierdo trasero</QuadrupedAnimalWithPawsAndTail.corePart.parts.12.customLabel>
  <QuadrupedAnimalWithPawsAndTail.corePart.parts.13.parts.0.customLabel>Pata trasera derecha</QuadrupedAnimalWithPawsAndTail.corePart.parts.13.parts.0.customLabel>
  <QuadrupedAnimalWithPawsAndTail.corePart.parts.13.customLabel>Pie trasero derecho</QuadrupedAnimalWithPawsAndTail.corePart.parts.13.customLabel>

  <QuadrupedAnimalWithHooves.label>Animal Cuadrúpedo</QuadrupedAnimalWithHooves.label>
  <QuadrupedAnimalWithHooves.corePart.parts.3.customLabel>Pulmón izquierdo</QuadrupedAnimalWithHooves.corePart.parts.3.customLabel>
  <QuadrupedAnimalWithHooves.corePart.parts.4.customLabel>Pulmón derecho</QuadrupedAnimalWithHooves.corePart.parts.4.customLabel>
  <QuadrupedAnimalWithHooves.corePart.parts.5.customLabel>Riñón izquierdo</QuadrupedAnimalWithHooves.corePart.parts.5.customLabel>
  <QuadrupedAnimalWithHooves.corePart.parts.6.customLabel>Riñón derecho</QuadrupedAnimalWithHooves.corePart.parts.6.customLabel>
  <QuadrupedAnimalWithHooves.corePart.parts.8.parts.0.parts.1.customLabel>Ojo izquierdo</QuadrupedAnimalWithHooves.corePart.parts.8.parts.0.parts.1.customLabel>
  <QuadrupedAnimalWithHooves.corePart.parts.8.parts.0.parts.2.customLabel>Ojo derecho</QuadrupedAnimalWithHooves.corePart.parts.8.parts.0.parts.2.customLabel>
  <QuadrupedAnimalWithHooves.corePart.parts.8.parts.0.parts.3.customLabel>Oído izquierdo</QuadrupedAnimalWithHooves.corePart.parts.8.parts.0.parts.3.customLabel>
  <QuadrupedAnimalWithHooves.corePart.parts.8.parts.0.parts.4.customLabel>Oído derecho</QuadrupedAnimalWithHooves.corePart.parts.8.parts.0.parts.4.customLabel>
  <QuadrupedAnimalWithHooves.corePart.parts.9.parts.0.customLabel>Casco delantero izquierdo</QuadrupedAnimalWithHooves.corePart.parts.9.parts.0.customLabel>
  <QuadrupedAnimalWithHooves.corePart.parts.9.customLabel>Pie izquierdo delantero</QuadrupedAnimalWithHooves.corePart.parts.9.customLabel>
  <QuadrupedAnimalWithHooves.corePart.parts.10.parts.0.customLabel>Casco derecho delantero</QuadrupedAnimalWithHooves.corePart.parts.10.parts.0.customLabel>
  <QuadrupedAnimalWithHooves.corePart.parts.10.customLabel>Pie derecho delantero</QuadrupedAnimalWithHooves.corePart.parts.10.customLabel>
  <QuadrupedAnimalWithHooves.corePart.parts.11.parts.0.customLabel>Casco trasero izquierdo</QuadrupedAnimalWithHooves.corePart.parts.11.parts.0.customLabel>
  <QuadrupedAnimalWithHooves.corePart.parts.11.customLabel>Pie izquierdo trasero</QuadrupedAnimalWithHooves.corePart.parts.11.customLabel>
  <QuadrupedAnimalWithHooves.corePart.parts.12.parts.0.customLabel>Casco trasero derecho</QuadrupedAnimalWithHooves.corePart.parts.12.parts.0.customLabel>
  <QuadrupedAnimalWithHooves.corePart.parts.12.customLabel>Pie trasero derecho</QuadrupedAnimalWithHooves.corePart.parts.12.customLabel>

  <QuadrupedAnimalWithHoovesAndHump.label>Animal Cuadrúpedo</QuadrupedAnimalWithHoovesAndHump.label>
  <QuadrupedAnimalWithHoovesAndHump.corePart.parts.3.customLabel>Pulmón izquierdo</QuadrupedAnimalWithHoovesAndHump.corePart.parts.3.customLabel>
  <QuadrupedAnimalWithHoovesAndHump.corePart.parts.4.customLabel>Pulmón derecho</QuadrupedAnimalWithHoovesAndHump.corePart.parts.4.customLabel>
  <QuadrupedAnimalWithHoovesAndHump.corePart.parts.5.customLabel>Riñón izquierdo</QuadrupedAnimalWithHoovesAndHump.corePart.parts.5.customLabel>
  <QuadrupedAnimalWithHoovesAndHump.corePart.parts.6.customLabel>Riñón derecho</QuadrupedAnimalWithHoovesAndHump.corePart.parts.6.customLabel>
  <QuadrupedAnimalWithHoovesAndHump.corePart.parts.9.parts.0.parts.1.customLabel>Ojo izquierdo</QuadrupedAnimalWithHoovesAndHump.corePart.parts.9.parts.0.parts.1.customLabel>
  <QuadrupedAnimalWithHoovesAndHump.corePart.parts.9.parts.0.parts.2.customLabel>Ojo derecho</QuadrupedAnimalWithHoovesAndHump.corePart.parts.9.parts.0.parts.2.customLabel>
  <QuadrupedAnimalWithHoovesAndHump.corePart.parts.9.parts.0.parts.3.customLabel>Oído izquierdo</QuadrupedAnimalWithHoovesAndHump.corePart.parts.9.parts.0.parts.3.customLabel>
  <QuadrupedAnimalWithHoovesAndHump.corePart.parts.9.parts.0.parts.4.customLabel>Oído derecho</QuadrupedAnimalWithHoovesAndHump.corePart.parts.9.parts.0.parts.4.customLabel>
  <QuadrupedAnimalWithHoovesAndHump.corePart.parts.10.parts.0.customLabel>Casco delantero izquierdo</QuadrupedAnimalWithHoovesAndHump.corePart.parts.10.parts.0.customLabel>
  <QuadrupedAnimalWithHoovesAndHump.corePart.parts.10.customLabel>Pie izquierdo delantero</QuadrupedAnimalWithHoovesAndHump.corePart.parts.10.customLabel>
  <QuadrupedAnimalWithHoovesAndHump.corePart.parts.11.parts.0.customLabel>Casco derecho delantero</QuadrupedAnimalWithHoovesAndHump.corePart.parts.11.parts.0.customLabel>
  <QuadrupedAnimalWithHoovesAndHump.corePart.parts.11.customLabel>Pie derecho delantero</QuadrupedAnimalWithHoovesAndHump.corePart.parts.11.customLabel>
  <QuadrupedAnimalWithHoovesAndHump.corePart.parts.12.parts.0.customLabel>Casco trasero izquierdo</QuadrupedAnimalWithHoovesAndHump.corePart.parts.12.parts.0.customLabel>
  <QuadrupedAnimalWithHoovesAndHump.corePart.parts.12.customLabel>Pie izquierdo trasero</QuadrupedAnimalWithHoovesAndHump.corePart.parts.12.customLabel>
  <QuadrupedAnimalWithHoovesAndHump.corePart.parts.13.parts.0.customLabel>Casco trasero derecho</QuadrupedAnimalWithHoovesAndHump.corePart.parts.13.parts.0.customLabel>
  <QuadrupedAnimalWithHoovesAndHump.corePart.parts.13.customLabel>Pie trasero derecho</QuadrupedAnimalWithHoovesAndHump.corePart.parts.13.customLabel>

  <QuadrupedAnimalWithHoovesAndTusks.label>Animal Cuadrúpedo</QuadrupedAnimalWithHoovesAndTusks.label>
  <QuadrupedAnimalWithHoovesAndTusks.corePart.parts.3.customLabel>Pulmón izquierdo</QuadrupedAnimalWithHoovesAndTusks.corePart.parts.3.customLabel>
  <QuadrupedAnimalWithHoovesAndTusks.corePart.parts.4.customLabel>Pulmón derecho</QuadrupedAnimalWithHoovesAndTusks.corePart.parts.4.customLabel>
  <QuadrupedAnimalWithHoovesAndTusks.corePart.parts.5.customLabel>Riñón izquierdo</QuadrupedAnimalWithHoovesAndTusks.corePart.parts.5.customLabel>
  <QuadrupedAnimalWithHoovesAndTusks.corePart.parts.6.customLabel>Riñón derecho</QuadrupedAnimalWithHoovesAndTusks.corePart.parts.6.customLabel>
  <QuadrupedAnimalWithHoovesAndTusks.corePart.parts.8.parts.0.parts.1.customLabel>Ojo izquierdo</QuadrupedAnimalWithHoovesAndTusks.corePart.parts.8.parts.0.parts.1.customLabel>
  <QuadrupedAnimalWithHoovesAndTusks.corePart.parts.8.parts.0.parts.2.customLabel>Ojo derecho</QuadrupedAnimalWithHoovesAndTusks.corePart.parts.8.parts.0.parts.2.customLabel>
  <QuadrupedAnimalWithHoovesAndTusks.corePart.parts.8.parts.0.parts.3.customLabel>Oído izquierdo</QuadrupedAnimalWithHoovesAndTusks.corePart.parts.8.parts.0.parts.3.customLabel>
  <QuadrupedAnimalWithHoovesAndTusks.corePart.parts.8.parts.0.parts.4.customLabel>Oído derecho</QuadrupedAnimalWithHoovesAndTusks.corePart.parts.8.parts.0.parts.4.customLabel>
  <QuadrupedAnimalWithHoovesAndTusks.corePart.parts.8.parts.0.parts.6.parts.0.customLabel>Colmillo izquierdo</QuadrupedAnimalWithHoovesAndTusks.corePart.parts.8.parts.0.parts.6.parts.0.customLabel>
  <QuadrupedAnimalWithHoovesAndTusks.corePart.parts.8.parts.0.parts.6.parts.1.customLabel>Colmillo derecho</QuadrupedAnimalWithHoovesAndTusks.corePart.parts.8.parts.0.parts.6.parts.1.customLabel>
  <QuadrupedAnimalWithHoovesAndTusks.corePart.parts.9.parts.0.customLabel>Casco delantero izquierdo</QuadrupedAnimalWithHoovesAndTusks.corePart.parts.9.parts.0.customLabel>
  <QuadrupedAnimalWithHoovesAndTusks.corePart.parts.9.customLabel>Pie izquierdo delantero</QuadrupedAnimalWithHoovesAndTusks.corePart.parts.9.customLabel>
  <QuadrupedAnimalWithHoovesAndTusks.corePart.parts.10.parts.0.customLabel>Casco derecho delantero</QuadrupedAnimalWithHoovesAndTusks.corePart.parts.10.parts.0.customLabel>
  <QuadrupedAnimalWithHoovesAndTusks.corePart.parts.10.customLabel>Pie derecho delantero</QuadrupedAnimalWithHoovesAndTusks.corePart.parts.10.customLabel>
  <QuadrupedAnimalWithHoovesAndTusks.corePart.parts.11.parts.0.customLabel>Casco trasero izquierdo</QuadrupedAnimalWithHoovesAndTusks.corePart.parts.11.parts.0.customLabel>
  <QuadrupedAnimalWithHoovesAndTusks.corePart.parts.11.customLabel>Pie izquierdo trasero</QuadrupedAnimalWithHoovesAndTusks.corePart.parts.11.customLabel>
  <QuadrupedAnimalWithHoovesAndTusks.corePart.parts.12.parts.0.customLabel>Casco trasero derecho</QuadrupedAnimalWithHoovesAndTusks.corePart.parts.12.parts.0.customLabel>
  <QuadrupedAnimalWithHoovesAndTusks.corePart.parts.12.customLabel>Pie trasero derecho</QuadrupedAnimalWithHoovesAndTusks.corePart.parts.12.customLabel>

  <QuadrupedAnimalWithHoovesTusksAndTrunk.label>Animal Cuadrúpedo</QuadrupedAnimalWithHoovesTusksAndTrunk.label>
  <QuadrupedAnimalWithHoovesTusksAndTrunk.corePart.parts.3.customLabel>Pulmón izquierdo</QuadrupedAnimalWithHoovesTusksAndTrunk.corePart.parts.3.customLabel>
  <QuadrupedAnimalWithHoovesTusksAndTrunk.corePart.parts.4.customLabel>Pulmón derecho</QuadrupedAnimalWithHoovesTusksAndTrunk.corePart.parts.4.customLabel>
  <QuadrupedAnimalWithHoovesTusksAndTrunk.corePart.parts.5.customLabel>Riñón izquierdo</QuadrupedAnimalWithHoovesTusksAndTrunk.corePart.parts.5.customLabel>
  <QuadrupedAnimalWithHoovesTusksAndTrunk.corePart.parts.6.customLabel>Riñón derecho</QuadrupedAnimalWithHoovesTusksAndTrunk.corePart.parts.6.customLabel>
  <QuadrupedAnimalWithHoovesTusksAndTrunk.corePart.parts.8.parts.0.parts.1.customLabel>Ojo izquierdo</QuadrupedAnimalWithHoovesTusksAndTrunk.corePart.parts.8.parts.0.parts.1.customLabel>
  <QuadrupedAnimalWithHoovesTusksAndTrunk.corePart.parts.8.parts.0.parts.2.customLabel>Ojo derecho</QuadrupedAnimalWithHoovesTusksAndTrunk.corePart.parts.8.parts.0.parts.2.customLabel>
  <QuadrupedAnimalWithHoovesTusksAndTrunk.corePart.parts.8.parts.0.parts.3.customLabel>Oído izquierdo</QuadrupedAnimalWithHoovesTusksAndTrunk.corePart.parts.8.parts.0.parts.3.customLabel>
  <QuadrupedAnimalWithHoovesTusksAndTrunk.corePart.parts.8.parts.0.parts.4.customLabel>Oído derecho</QuadrupedAnimalWithHoovesTusksAndTrunk.corePart.parts.8.parts.0.parts.4.customLabel>
  <QuadrupedAnimalWithHoovesTusksAndTrunk.corePart.parts.8.parts.0.parts.6.parts.0.customLabel>Colmillo izquierdo</QuadrupedAnimalWithHoovesTusksAndTrunk.corePart.parts.8.parts.0.parts.6.parts.0.customLabel>
  <QuadrupedAnimalWithHoovesTusksAndTrunk.corePart.parts.8.parts.0.parts.6.parts.1.customLabel>Colmillo derecho</QuadrupedAnimalWithHoovesTusksAndTrunk.corePart.parts.8.parts.0.parts.6.parts.1.customLabel>
  <QuadrupedAnimalWithHoovesTusksAndTrunk.corePart.parts.9.parts.0.customLabel>Casco delantero izquierdo</QuadrupedAnimalWithHoovesTusksAndTrunk.corePart.parts.9.parts.0.customLabel>
  <QuadrupedAnimalWithHoovesTusksAndTrunk.corePart.parts.9.customLabel>Pie izquierdo delantero</QuadrupedAnimalWithHoovesTusksAndTrunk.corePart.parts.9.customLabel>
  <QuadrupedAnimalWithHoovesTusksAndTrunk.corePart.parts.10.parts.0.customLabel>Casco derecho delantero</QuadrupedAnimalWithHoovesTusksAndTrunk.corePart.parts.10.parts.0.customLabel>
  <QuadrupedAnimalWithHoovesTusksAndTrunk.corePart.parts.10.customLabel>Pie derecho delantero</QuadrupedAnimalWithHoovesTusksAndTrunk.corePart.parts.10.customLabel>
  <QuadrupedAnimalWithHoovesTusksAndTrunk.corePart.parts.11.parts.0.customLabel>Casco trasero izquierdo</QuadrupedAnimalWithHoovesTusksAndTrunk.corePart.parts.11.parts.0.customLabel>
  <QuadrupedAnimalWithHoovesTusksAndTrunk.corePart.parts.11.customLabel>Pie izquierdo trasero</QuadrupedAnimalWithHoovesTusksAndTrunk.corePart.parts.11.customLabel>
  <QuadrupedAnimalWithHoovesTusksAndTrunk.corePart.parts.12.parts.0.customLabel>Casco trasero derecho</QuadrupedAnimalWithHoovesTusksAndTrunk.corePart.parts.12.parts.0.customLabel>
  <QuadrupedAnimalWithHoovesTusksAndTrunk.corePart.parts.12.customLabel>Pie trasero derecho</QuadrupedAnimalWithHoovesTusksAndTrunk.corePart.parts.12.customLabel>

  <QuadrupedAnimalWithHoovesAndHorn.label>Animal Cuadrúpedo</QuadrupedAnimalWithHoovesAndHorn.label>
  <QuadrupedAnimalWithHoovesAndHorn.corePart.parts.3.customLabel>Pulmón izquierdo</QuadrupedAnimalWithHoovesAndHorn.corePart.parts.3.customLabel>
  <QuadrupedAnimalWithHoovesAndHorn.corePart.parts.4.customLabel>Pulmón derecho</QuadrupedAnimalWithHoovesAndHorn.corePart.parts.4.customLabel>
  <QuadrupedAnimalWithHoovesAndHorn.corePart.parts.5.customLabel>Riñón izquierdo</QuadrupedAnimalWithHoovesAndHorn.corePart.parts.5.customLabel>
  <QuadrupedAnimalWithHoovesAndHorn.corePart.parts.6.customLabel>Riñón derecho</QuadrupedAnimalWithHoovesAndHorn.corePart.parts.6.customLabel>
  <QuadrupedAnimalWithHoovesAndHorn.corePart.parts.8.parts.0.parts.1.customLabel>Ojo izquierdo</QuadrupedAnimalWithHoovesAndHorn.corePart.parts.8.parts.0.parts.1.customLabel>
  <QuadrupedAnimalWithHoovesAndHorn.corePart.parts.8.parts.0.parts.2.customLabel>Ojo derecho</QuadrupedAnimalWithHoovesAndHorn.corePart.parts.8.parts.0.parts.2.customLabel>
  <QuadrupedAnimalWithHoovesAndHorn.corePart.parts.8.parts.0.parts.3.customLabel>Oído izquierdo</QuadrupedAnimalWithHoovesAndHorn.corePart.parts.8.parts.0.parts.3.customLabel>
  <QuadrupedAnimalWithHoovesAndHorn.corePart.parts.8.parts.0.parts.4.customLabel>Oído derecho</QuadrupedAnimalWithHoovesAndHorn.corePart.parts.8.parts.0.parts.4.customLabel>
  <QuadrupedAnimalWithHoovesAndHorn.corePart.parts.9.parts.0.customLabel>Casco delantero izquierdo</QuadrupedAnimalWithHoovesAndHorn.corePart.parts.9.parts.0.customLabel>
  <QuadrupedAnimalWithHoovesAndHorn.corePart.parts.9.customLabel>Pie izquierdo delantero</QuadrupedAnimalWithHoovesAndHorn.corePart.parts.9.customLabel>
  <QuadrupedAnimalWithHoovesAndHorn.corePart.parts.10.parts.0.customLabel>Casco derecho delantero</QuadrupedAnimalWithHoovesAndHorn.corePart.parts.10.parts.0.customLabel>
  <QuadrupedAnimalWithHoovesAndHorn.corePart.parts.10.customLabel>Pie derecho delantero</QuadrupedAnimalWithHoovesAndHorn.corePart.parts.10.customLabel>
  <QuadrupedAnimalWithHoovesAndHorn.corePart.parts.11.parts.0.customLabel>Casco trasero izquierdo</QuadrupedAnimalWithHoovesAndHorn.corePart.parts.11.parts.0.customLabel>
  <QuadrupedAnimalWithHoovesAndHorn.corePart.parts.11.customLabel>Pie izquierdo trasero</QuadrupedAnimalWithHoovesAndHorn.corePart.parts.11.customLabel>
  <QuadrupedAnimalWithHoovesAndHorn.corePart.parts.12.parts.0.customLabel>Casco trasero derecho</QuadrupedAnimalWithHoovesAndHorn.corePart.parts.12.parts.0.customLabel>
  <QuadrupedAnimalWithHoovesAndHorn.corePart.parts.12.customLabel>Pie trasero derecho</QuadrupedAnimalWithHoovesAndHorn.corePart.parts.12.customLabel>

  <QuadrupedAnimalWithClawsTailAndJowl.label>Animal Cuadrúpedo</QuadrupedAnimalWithClawsTailAndJowl.label>
  <QuadrupedAnimalWithClawsTailAndJowl.corePart.parts.4.customLabel>Pulmón izquierdo</QuadrupedAnimalWithClawsTailAndJowl.corePart.parts.4.customLabel>
  <QuadrupedAnimalWithClawsTailAndJowl.corePart.parts.5.customLabel>Pulmón derecho</QuadrupedAnimalWithClawsTailAndJowl.corePart.parts.5.customLabel>
  <QuadrupedAnimalWithClawsTailAndJowl.corePart.parts.6.customLabel>Riñón izquierdo</QuadrupedAnimalWithClawsTailAndJowl.corePart.parts.6.customLabel>
  <QuadrupedAnimalWithClawsTailAndJowl.corePart.parts.7.customLabel>Riñón derecho</QuadrupedAnimalWithClawsTailAndJowl.corePart.parts.7.customLabel>
  <QuadrupedAnimalWithClawsTailAndJowl.corePart.parts.9.parts.0.parts.1.customLabel>Ojo izquierdo</QuadrupedAnimalWithClawsTailAndJowl.corePart.parts.9.parts.0.parts.1.customLabel>
  <QuadrupedAnimalWithClawsTailAndJowl.corePart.parts.9.parts.0.parts.2.customLabel>Ojo derecho</QuadrupedAnimalWithClawsTailAndJowl.corePart.parts.9.parts.0.parts.2.customLabel>
  <QuadrupedAnimalWithClawsTailAndJowl.corePart.parts.9.parts.0.parts.3.customLabel>Oído izquierdo</QuadrupedAnimalWithClawsTailAndJowl.corePart.parts.9.parts.0.parts.3.customLabel>
  <QuadrupedAnimalWithClawsTailAndJowl.corePart.parts.9.parts.0.parts.4.customLabel>Oído derecho</QuadrupedAnimalWithClawsTailAndJowl.corePart.parts.9.parts.0.parts.4.customLabel>
  <QuadrupedAnimalWithClawsTailAndJowl.corePart.parts.10.parts.0.customLabel>Pie izquierdo delantero primera garra</QuadrupedAnimalWithClawsTailAndJowl.corePart.parts.10.parts.0.customLabel>
  <QuadrupedAnimalWithClawsTailAndJowl.corePart.parts.10.parts.1.customLabel>Pie izquierdo delantero segunda garra</QuadrupedAnimalWithClawsTailAndJowl.corePart.parts.10.parts.1.customLabel>
  <QuadrupedAnimalWithClawsTailAndJowl.corePart.parts.10.parts.2.customLabel>Pie izquierdo delantero tercera uña</QuadrupedAnimalWithClawsTailAndJowl.corePart.parts.10.parts.2.customLabel>
  <QuadrupedAnimalWithClawsTailAndJowl.corePart.parts.10.parts.3.customLabel>Pie izquierdo delantero cuarta uña</QuadrupedAnimalWithClawsTailAndJowl.corePart.parts.10.parts.3.customLabel>
  <QuadrupedAnimalWithClawsTailAndJowl.corePart.parts.10.parts.4.customLabel>Pie izquierdo delantero quinta uña</QuadrupedAnimalWithClawsTailAndJowl.corePart.parts.10.parts.4.customLabel>
  <QuadrupedAnimalWithClawsTailAndJowl.corePart.parts.10.customLabel>Pie izquierdo delantero</QuadrupedAnimalWithClawsTailAndJowl.corePart.parts.10.customLabel>
  <QuadrupedAnimalWithClawsTailAndJowl.corePart.parts.11.parts.0.customLabel>Pie derecho delantero primera garra</QuadrupedAnimalWithClawsTailAndJowl.corePart.parts.11.parts.0.customLabel>
  <QuadrupedAnimalWithClawsTailAndJowl.corePart.parts.11.parts.1.customLabel>Pie derecho delantero segunda garra</QuadrupedAnimalWithClawsTailAndJowl.corePart.parts.11.parts.1.customLabel>
  <QuadrupedAnimalWithClawsTailAndJowl.corePart.parts.11.parts.2.customLabel>Pie derecho delantero tercera uña</QuadrupedAnimalWithClawsTailAndJowl.corePart.parts.11.parts.2.customLabel>
  <QuadrupedAnimalWithClawsTailAndJowl.corePart.parts.11.parts.3.customLabel>Pie derecho delantero cuarta uña</QuadrupedAnimalWithClawsTailAndJowl.corePart.parts.11.parts.3.customLabel>
  <QuadrupedAnimalWithClawsTailAndJowl.corePart.parts.11.parts.4.customLabel>Pie derecho delantero quinta uña</QuadrupedAnimalWithClawsTailAndJowl.corePart.parts.11.parts.4.customLabel>
  <QuadrupedAnimalWithClawsTailAndJowl.corePart.parts.11.customLabel>Pie derecho delantero</QuadrupedAnimalWithClawsTailAndJowl.corePart.parts.11.customLabel>
  <QuadrupedAnimalWithClawsTailAndJowl.corePart.parts.12.parts.0.customLabel>Pie izquierdo trasero primera garra</QuadrupedAnimalWithClawsTailAndJowl.corePart.parts.12.parts.0.customLabel>
  <QuadrupedAnimalWithClawsTailAndJowl.corePart.parts.12.parts.1.customLabel>Pie izquierdo trasero segunda garra</QuadrupedAnimalWithClawsTailAndJowl.corePart.parts.12.parts.1.customLabel>
  <QuadrupedAnimalWithClawsTailAndJowl.corePart.parts.12.parts.2.customLabel>Pie izquierdo trasero tercera uña</QuadrupedAnimalWithClawsTailAndJowl.corePart.parts.12.parts.2.customLabel>
  <QuadrupedAnimalWithClawsTailAndJowl.corePart.parts.12.parts.3.customLabel>Pie izquierdo trasero cuarta uña</QuadrupedAnimalWithClawsTailAndJowl.corePart.parts.12.parts.3.customLabel>
  <QuadrupedAnimalWithClawsTailAndJowl.corePart.parts.12.parts.4.customLabel>Pie izquierdo trasero quinta uña</QuadrupedAnimalWithClawsTailAndJowl.corePart.parts.12.parts.4.customLabel>
  <QuadrupedAnimalWithClawsTailAndJowl.corePart.parts.12.customLabel>Pie izquierdo trasero</QuadrupedAnimalWithClawsTailAndJowl.corePart.parts.12.customLabel>
  <QuadrupedAnimalWithClawsTailAndJowl.corePart.parts.13.parts.0.customLabel>Pie trasero derecho primera garra</QuadrupedAnimalWithClawsTailAndJowl.corePart.parts.13.parts.0.customLabel>
  <QuadrupedAnimalWithClawsTailAndJowl.corePart.parts.13.parts.1.customLabel>Pie trasero derecho segunda garra</QuadrupedAnimalWithClawsTailAndJowl.corePart.parts.13.parts.1.customLabel>
  <QuadrupedAnimalWithClawsTailAndJowl.corePart.parts.13.parts.2.customLabel>Pie trasero derecho tercera uña</QuadrupedAnimalWithClawsTailAndJowl.corePart.parts.13.parts.2.customLabel>
  <QuadrupedAnimalWithClawsTailAndJowl.corePart.parts.13.parts.3.customLabel>Pie trasero derecho cuarta uña</QuadrupedAnimalWithClawsTailAndJowl.corePart.parts.13.parts.3.customLabel>
  <QuadrupedAnimalWithClawsTailAndJowl.corePart.parts.13.parts.4.customLabel>Pie trasero derecho quinta uña</QuadrupedAnimalWithClawsTailAndJowl.corePart.parts.13.parts.4.customLabel>
  <QuadrupedAnimalWithClawsTailAndJowl.corePart.parts.13.customLabel>Pie trasero derecho</QuadrupedAnimalWithClawsTailAndJowl.corePart.parts.13.customLabel>

  <TurtleLike.label>Tortugoide</TurtleLike.label>
  <TurtleLike.corePart.parts.5.customLabel>Pulmón izquierdo</TurtleLike.corePart.parts.5.customLabel>
  <TurtleLike.corePart.parts.6.customLabel>Pulmón derecho</TurtleLike.corePart.parts.6.customLabel>
  <TurtleLike.corePart.parts.7.customLabel>Riñón izquierdo</TurtleLike.corePart.parts.7.customLabel>
  <TurtleLike.corePart.parts.8.customLabel>Riñón derecho</TurtleLike.corePart.parts.8.customLabel>
  <TurtleLike.corePart.parts.10.parts.1.customLabel>Ojo izquierdo</TurtleLike.corePart.parts.10.parts.1.customLabel>
  <TurtleLike.corePart.parts.10.parts.2.customLabel>Ojo derecho</TurtleLike.corePart.parts.10.parts.2.customLabel>
  <TurtleLike.corePart.parts.11.customLabel>Pie izquierdo delantero</TurtleLike.corePart.parts.11.customLabel>
  <TurtleLike.corePart.parts.12.customLabel>Pie derecho delantero</TurtleLike.corePart.parts.12.customLabel>
  <TurtleLike.corePart.parts.13.customLabel>Pie izquierdo trasero</TurtleLike.corePart.parts.13.customLabel>
  <TurtleLike.corePart.parts.14.customLabel>Pie trasero derecho</TurtleLike.corePart.parts.14.customLabel>

  <Monkey.label>Mono</Monkey.label>
  <Monkey.corePart.parts.1.customLabel>Clavícula izquierda</Monkey.corePart.parts.1.customLabel>
  <Monkey.corePart.parts.2.customLabel>Clavícula derecha</Monkey.corePart.parts.2.customLabel>
  <Monkey.corePart.parts.9.customLabel>Pulmón izquierdo</Monkey.corePart.parts.9.customLabel>
  <Monkey.corePart.parts.10.customLabel>Pulmón derecho</Monkey.corePart.parts.10.customLabel>
  <Monkey.corePart.parts.11.customLabel>Riñón izquierdo</Monkey.corePart.parts.11.customLabel>
  <Monkey.corePart.parts.12.customLabel>Riñón derecho</Monkey.corePart.parts.12.customLabel>
  <Monkey.corePart.parts.14.parts.0.parts.1.customLabel>Ojo izquierdo</Monkey.corePart.parts.14.parts.0.parts.1.customLabel>
  <Monkey.corePart.parts.14.parts.0.parts.2.customLabel>Ojo derecho</Monkey.corePart.parts.14.parts.0.parts.2.customLabel>
  <Monkey.corePart.parts.14.parts.0.parts.3.customLabel>Oído izquierdo</Monkey.corePart.parts.14.parts.0.parts.3.customLabel>
  <Monkey.corePart.parts.14.parts.0.parts.4.customLabel>Oído derecho</Monkey.corePart.parts.14.parts.0.parts.4.customLabel>
  <Monkey.corePart.parts.15.parts.0.parts.0.customLabel>Húmero izquierdo</Monkey.corePart.parts.15.parts.0.parts.0.customLabel>
  <Monkey.corePart.parts.15.parts.0.parts.1.customLabel>Radio izquierdo</Monkey.corePart.parts.15.parts.0.parts.1.customLabel>
  <Monkey.corePart.parts.15.parts.0.parts.2.parts.0.customLabel>Meñique izquierdo</Monkey.corePart.parts.15.parts.0.parts.2.parts.0.customLabel>
  <Monkey.corePart.parts.15.parts.0.parts.2.parts.1.customLabel>Dedo anular izquierdo</Monkey.corePart.parts.15.parts.0.parts.2.parts.1.customLabel>
  <Monkey.corePart.parts.15.parts.0.parts.2.parts.2.customLabel>Dedo medio izquierdo</Monkey.corePart.parts.15.parts.0.parts.2.parts.2.customLabel>
  <Monkey.corePart.parts.15.parts.0.parts.2.parts.3.customLabel>Dedo índice izquierdo</Monkey.corePart.parts.15.parts.0.parts.2.parts.3.customLabel>
  <Monkey.corePart.parts.15.parts.0.parts.2.parts.4.customLabel>Pulgar izquierdo</Monkey.corePart.parts.15.parts.0.parts.2.parts.4.customLabel>
  <Monkey.corePart.parts.15.parts.0.parts.2.customLabel>Mano izquierda</Monkey.corePart.parts.15.parts.0.parts.2.customLabel>
  <Monkey.corePart.parts.15.parts.0.customLabel>Brazo izquierdo</Monkey.corePart.parts.15.parts.0.customLabel>
  <Monkey.corePart.parts.15.customLabel>Hombro izquierdo</Monkey.corePart.parts.15.customLabel>
  <Monkey.corePart.parts.16.parts.0.parts.0.customLabel>Húmero derecho</Monkey.corePart.parts.16.parts.0.parts.0.customLabel>
  <Monkey.corePart.parts.16.parts.0.parts.1.customLabel>Radio correcto</Monkey.corePart.parts.16.parts.0.parts.1.customLabel>
  <Monkey.corePart.parts.16.parts.0.parts.2.parts.0.customLabel>Meñique derecho</Monkey.corePart.parts.16.parts.0.parts.2.parts.0.customLabel>
  <Monkey.corePart.parts.16.parts.0.parts.2.parts.1.customLabel>Dedo anular derecho</Monkey.corePart.parts.16.parts.0.parts.2.parts.1.customLabel>
  <Monkey.corePart.parts.16.parts.0.parts.2.parts.2.customLabel>Dedo medio derecho</Monkey.corePart.parts.16.parts.0.parts.2.parts.2.customLabel>
  <Monkey.corePart.parts.16.parts.0.parts.2.parts.3.customLabel>Dedo índice derecho</Monkey.corePart.parts.16.parts.0.parts.2.parts.3.customLabel>
  <Monkey.corePart.parts.16.parts.0.parts.2.parts.4.customLabel>Pulgar derecho</Monkey.corePart.parts.16.parts.0.parts.2.parts.4.customLabel>
  <Monkey.corePart.parts.16.parts.0.parts.2.customLabel>Mano derecha</Monkey.corePart.parts.16.parts.0.parts.2.customLabel>
  <Monkey.corePart.parts.16.parts.0.customLabel>Brazo derecho</Monkey.corePart.parts.16.parts.0.customLabel>
  <Monkey.corePart.parts.16.customLabel>Hombro derecho</Monkey.corePart.parts.16.customLabel>
  <Monkey.corePart.parts.17.parts.0.customLabel>Fémur izquierdo</Monkey.corePart.parts.17.parts.0.customLabel>
  <Monkey.corePart.parts.17.parts.1.customLabel>Tibia izquierda</Monkey.corePart.parts.17.parts.1.customLabel>
  <Monkey.corePart.parts.17.parts.2.parts.0.customLabel>Dedo pequeño del pie izquierdo</Monkey.corePart.parts.17.parts.2.parts.0.customLabel>
  <Monkey.corePart.parts.17.parts.2.parts.1.customLabel>Cuarto dedo del pie izquierdo</Monkey.corePart.parts.17.parts.2.parts.1.customLabel>
  <Monkey.corePart.parts.17.parts.2.parts.2.customLabel>Dedo medio del pie izquierdo</Monkey.corePart.parts.17.parts.2.parts.2.customLabel>
  <Monkey.corePart.parts.17.parts.2.parts.3.customLabel>Segundo dedo del pie izquierdo</Monkey.corePart.parts.17.parts.2.parts.3.customLabel>
  <Monkey.corePart.parts.17.parts.2.parts.4.customLabel>Dedo gordo del pie izquierdo</Monkey.corePart.parts.17.parts.2.parts.4.customLabel>
  <Monkey.corePart.parts.17.parts.2.customLabel>Pie izquierdo</Monkey.corePart.parts.17.parts.2.customLabel>
  <Monkey.corePart.parts.17.customLabel>Pierna izquierda</Monkey.corePart.parts.17.customLabel>
  <Monkey.corePart.parts.18.parts.0.customLabel>Fémur derecho</Monkey.corePart.parts.18.parts.0.customLabel>
  <Monkey.corePart.parts.18.parts.1.customLabel>Tibia derecha</Monkey.corePart.parts.18.parts.1.customLabel>
  <Monkey.corePart.parts.18.parts.2.parts.0.customLabel>Dedo pequeño derecho</Monkey.corePart.parts.18.parts.2.parts.0.customLabel>
  <Monkey.corePart.parts.18.parts.2.parts.1.customLabel>Cuarto dedo del pie derecho</Monkey.corePart.parts.18.parts.2.parts.1.customLabel>
  <Monkey.corePart.parts.18.parts.2.parts.2.customLabel>Dedo medio derecho del pie</Monkey.corePart.parts.18.parts.2.parts.2.customLabel>
  <Monkey.corePart.parts.18.parts.2.parts.3.customLabel>Segundo dedo del pie derecho</Monkey.corePart.parts.18.parts.2.parts.3.customLabel>
  <Monkey.corePart.parts.18.parts.2.parts.4.customLabel>Dedo gordo del pie derecho</Monkey.corePart.parts.18.parts.2.parts.4.customLabel>
  <Monkey.corePart.parts.18.parts.2.customLabel>Pie derecho</Monkey.corePart.parts.18.parts.2.customLabel>
  <Monkey.corePart.parts.18.customLabel>Pierna derecha</Monkey.corePart.parts.18.customLabel>

</LanguageData>
