<?xml version="1.0" encoding="utf-8"?>
<LanguageData>

    <TropicalRainforest.label>Selva Tropical</TropicalRainforest.label>
    <TropicalRainforest.description>Una jungla espesa y húmeda. La densidad de la vegetación, las constantes enfermedades y la agresividad de los animales hacen difícil para construir y sobrevivir, por estas razones algunos exploradores la llaman el "infierno verde".</TropicalRainforest.description>

    <TropicalSwamp.label>Pantano Tropical</TropicalSwamp.label>
    <TropicalSwamp.description>Una espesa selva con mucho pantano y barro por doquier. Moverse en este lugar es difícil, hay muy poco espacio para contruir estructuras pesadas, los animales son muy agresivos y las enfermedades son constantes, sus condiciones haceb de este lugar una pesadilla para vivir.</TropicalSwamp.description>


</LanguageData>
